CURandRTC/PyCURandRTC.dll
CURandRTC/__init__.py
CURandRTC/libPyCURandRTC.so
CURandRTC-0.1.7.dist-info/METADATA
CURandRTC-0.1.7.dist-info/WHEEL
CURandRTC-0.1.7.dist-info/top_level.txt
CURandRTC-0.1.7.dist-info/RECORD
