Metadata-Version: 2.1
Name: CURandRTC
Version: 0.1.7
Summary: Random number generation module based on ThrustRTC
Home-page: https://github.com/fynv/CURandRTC
Author: Fei Yang
Author-email: hyangfeih@gmail.com
License: Anti 996
Keywords: GPU CUDA Random XORWOR
Platform: UNKNOWN
Requires-Dist: ThrustRTC
